{
    "0": {
        "text": {
            "text": "earphone,headphone,head_band,top_band",
            "id": 0
        },
        "file": "original-94"
    },
    "1": {
        "text": {
            "text": "earphone,headphone,head_band,top_band",
            "id": 1
        },
        "file": "original-35"
    },
    "2": {
        "text": {
            "text": "earphone,headphone,head_band,top_band",
            "id": 2
        },
        "file": "original-39"
    },
    "3": {
        "text": {
            "text": "earphone,headphone,head_band,top_band",
            "id": 3
        },
        "file": "original-38"
    },
    "4": {
        "text": {
            "text": "earphone,headphone,head_band,top_band",
            "id": 4
        },
        "file": "original-34"
    },
    "5": {
        "text": {
            "text": "earphone,headphone,head_band,top_band",
            "id": 5
        },
        "file": "original-118"
    },
    "6": {
        "text": {
            "text": "earphone,headphone,head_band,top_band",
            "id": 6
        },
        "file": "original-71"
    },
    "7": {
        "text": {
            "text": "earphone,headphone,head_band,top_band",
            "id": 7
        },
        "file": "original-70"
    },
    "8": {
        "text": {
            "text": "earphone,headphone,head_band,top_band",
            "id": 8
        },
        "file": "original-60"
    },
    "9": {
        "text": {
            "text": "earphone,headphone,head_band,top_band",
            "id": 9
        },
        "file": "original-62"
    },
    "10": {
        "text": {
            "text": "earphone,headphone,head_band,top_band",
            "id": 10
        },
        "file": "original-114"
    },
    "11": {
        "text": {
            "text": "earphone,headphone,head_band,top_band",
            "id": 11
        },
        "file": "original-33"
    },
    "12": {
        "text": {
            "text": "earphone,headphone,head_band,top_band",
            "id": 12
        },
        "file": "original-78"
    },
    "13": {
        "text": {
            "text": "earphone,headphone,head_band,top_band",
            "id": 13
        },
        "file": "original-73"
    },
    "14": {
        "text": {
            "text": "earphone,headphone,head_band,top_band",
            "id": 14
        },
        "file": "original-68"
    },
    "15": {
        "text": {
            "text": "earphone,headphone,head_band,top_band",
            "id": 15
        },
        "file": "original-69"
    },
    "16": {
        "text": {
            "text": "earphone,headphone,head_band,top_band",
            "id": 16
        },
        "file": "original-74"
    },
    "17": {
        "text": {
            "text": "earphone,headphone,head_band,top_band",
            "id": 17
        },
        "file": "original-77"
    },
    "18": {
        "text": {
            "text": "earphone,headphone,head_band,top_band",
            "id": 18
        },
        "file": "original-76"
    },
    "19": {
        "text": {
            "text": "earphone,headphone,head_band,top_band",
            "id": 19
        },
        "file": "original-79"
    },
    "20": {
        "text": {
            "text": "earphone,headphone,head_band,top_band",
            "id": 20
        },
        "file": "original-72"
    },
    "21": {
        "text": {
            "text": "earphone,headphone,head_band,top_band",
            "id": 21
        },
        "file": "original-75"
    },
    "22": {
        "text": {
            "text": "earphone,headphone,head_band,top_band",
            "id": 22
        },
        "file": "original-36"
    },
    "23": {
        "text": {
            "text": "earphone,headphone,head_band,top_band",
            "id": 23
        },
        "file": "original-37"
    },
    "24": {
        "text": {
            "text": "earphone,headphone,head_band,top_band",
            "id": 24
        },
        "file": "original-40"
    },
    "25": {
        "text": {
            "text": "earphone,headphone,head_band,top_band",
            "id": 25
        },
        "file": "original-41"
    },
    "26": {
        "text": {
            "text": "earphone,headphone,head_band,top_band",
            "id": 26
        },
        "file": "original-30"
    },
    "27": {
        "text": {
            "text": "earphone,headphone,head_band,top_band",
            "id": 27
        },
        "file": "original-61"
    },
    "28": {
        "text": {
            "text": "earphone,headphone,head_band,top_band",
            "id": 28
        },
        "file": "original-152"
    },
    "29": {
        "text": {
            "text": "earphone,headphone,head_band,top_band",
            "id": 29
        },
        "file": "original-156"
    },
    "30": {
        "text": {
            "text": "earphone,headphone,head_band,top_band",
            "id": 30
        },
        "file": "original-4"
    },
    "31": {
        "text": {
            "text": "earphone,headphone,head_band,top_band",
            "id": 31
        },
        "file": "original-5"
    },
    "32": {
        "text": {
            "text": "earphone,headphone,head_band,top_band",
            "id": 32
        },
        "file": "original-8"
    },
    "33": {
        "text": {
            "text": "earphone,headphone,head_band,top_band",
            "id": 33
        },
        "file": "original-7"
    },
    "34": {
        "text": {
            "text": "earphone,headphone,head_band,top_band",
            "id": 34
        },
        "file": "original-10"
    },
    "35": {
        "text": {
            "text": "earphone,headphone,head_band,top_band",
            "id": 35
        },
        "file": "original-6"
    },
    "36": {
        "text": {
            "text": "earphone,headphone,head_band,top_band",
            "id": 36
        },
        "file": "original-12"
    },
    "37": {
        "text": {
            "text": "earphone,headphone,head_band,top_band",
            "id": 37
        },
        "file": "original-2"
    },
    "38": {
        "text": {
            "text": "earphone,headphone,head_band,top_band",
            "id": 38
        },
        "file": "original-3"
    },
    "39": {
        "text": {
            "text": "earphone,headphone,head_band,top_band",
            "id": 39
        },
        "file": "original-42"
    },
    "40": {
        "text": {
            "text": "earphone,headphone,head_band,top_band",
            "id": 40
        },
        "file": "original-50"
    },
    "41": {
        "text": {
            "text": "earphone,headphone,head_band,top_band",
            "id": 41
        },
        "file": "original-43"
    },
    "42": {
        "text": {
            "text": "earphone,headphone,head_band,top_band",
            "id": 42
        },
        "file": "original-51"
    },
    "43": {
        "text": {
            "text": "earphone,headphone,head_band,top_band",
            "id": 43
        },
        "file": "original-29"
    },
    "44": {
        "text": {
            "text": "earphone,headphone,head_band,top_band",
            "id": 44
        },
        "file": "original-44"
    },
    "45": {
        "text": {
            "text": "earphone,headphone,head_band,top_band",
            "id": 45
        },
        "file": "original-32"
    },
    "46": {
        "text": {
            "text": "earphone,headphone,head_band,top_band",
            "id": 46
        },
        "file": "original-52"
    },
    "47": {
        "text": {
            "text": "earphone,headphone,head_band,top_band",
            "id": 47
        },
        "file": "original-53"
    },
    "48": {
        "text": {
            "text": "earphone,headphone,head_band,top_band",
            "id": 48
        },
        "file": "original-55"
    },
    "49": {
        "text": {
            "text": "earphone,headphone,head_band,top_band",
            "id": 49
        },
        "file": "original-54"
    },
    "50": {
        "text": {
            "text": "earphone,headphone,head_band,top_band",
            "id": 50
        },
        "file": "original-45"
    },
    "51": {
        "text": {
            "text": "earphone,headphone,head_band,top_band",
            "id": 51
        },
        "file": "original-56"
    },
    "52": {
        "text": {
            "text": "earphone,headphone,head_band,top_band",
            "id": 52
        },
        "file": "original-46"
    },
    "53": {
        "text": {
            "text": "earphone,headphone,head_band,top_band",
            "id": 53
        },
        "file": "original-59"
    },
    "54": {
        "text": {
            "text": "earphone,headphone,head_band,top_band",
            "id": 54
        },
        "file": "original-58"
    },
    "55": {
        "text": {
            "text": "earphone,headphone,head_band,top_band",
            "id": 55
        },
        "file": "original-57"
    },
    "56": {
        "text": {
            "text": "earphone,headphone,head_band,top_band",
            "id": 56
        },
        "file": "original-31"
    },
    "57": {
        "text": {
            "text": "earphone,headphone,head_band,top_band",
            "id": 57
        },
        "file": "original-49"
    },
    "58": {
        "text": {
            "text": "earphone,headphone,head_band,top_band",
            "id": 58
        },
        "file": "original-48"
    },
    "59": {
        "text": {
            "text": "earphone,headphone,head_band,top_band",
            "id": 59
        },
        "file": "original-47"
    },
    "60": {
        "text": {
            "text": "earphone,headphone,head_band,top_band",
            "id": 60
        },
        "file": "original-63"
    },
    "61": {
        "text": {
            "text": "earphone,headphone,head_band,top_band",
            "id": 61
        },
        "file": "original-11"
    },
    "62": {
        "text": {
            "text": "earphone,headphone,head_band,top_band",
            "id": 62
        },
        "file": "original-13"
    },
    "63": {
        "text": {
            "text": "earphone,headphone,head_band,top_band",
            "id": 63
        },
        "file": "original-9"
    },
    "64": {
        "text": {
            "text": "earphone,headphone,head_band,top_band",
            "id": 64
        },
        "file": "original-155"
    },
    "65": {
        "text": {
            "text": "earphone,headphone,head_band,top_band",
            "id": 65
        },
        "file": "original-153"
    },
    "66": {
        "text": {
            "text": "earphone,headphone,head_band,top_band",
            "id": 66
        },
        "file": "original-154"
    },
    "67": {
        "text": {
            "text": "earphone,headphone,head_band,top_band",
            "id": 67
        },
        "file": "original-115"
    },
    "68": {
        "text": {
            "text": "earphone,headphone,head_band,top_band",
            "id": 68
        },
        "file": "original-116"
    },
    "69": {
        "text": {
            "text": "earphone,headphone,head_band,top_band",
            "id": 69
        },
        "file": "original-117"
    },
    "70": {
        "text": {
            "text": "earphone,headphone,earcup_unit,earcup_frame",
            "id": 70
        },
        "file": "original-126"
    },
    "71": {
        "text": {
            "text": "earphone,headphone,earcup_unit,earcup_frame",
            "id": 71
        },
        "file": "original-128"
    },
    "72": {
        "text": {
            "text": "earphone,headphone,earcup_unit,earcup_frame",
            "id": 72
        },
        "file": "original-127"
    },
    "73": {
        "text": {
            "text": "earphone,headphone,earcup_unit,earcup_frame",
            "id": 73
        },
        "file": "original-131"
    },
    "74": {
        "text": {
            "text": "earphone,headphone,earcup_unit,earcup_frame",
            "id": 74
        },
        "file": "original-173"
    },
    "75": {
        "text": {
            "text": "earphone,headphone,earcup_unit,earcup_frame",
            "id": 75
        },
        "file": "original-176"
    },
    "76": {
        "text": {
            "text": "earphone,headphone,earcup_unit,earcup_frame",
            "id": 76
        },
        "file": "original-170"
    },
    "77": {
        "text": {
            "text": "earphone,headphone,earcup_unit,earcup_frame",
            "id": 77
        },
        "file": "original-177"
    },
    "78": {
        "text": {
            "text": "earphone,headphone,earcup_unit,earcup_frame",
            "id": 78
        },
        "file": "original-146"
    },
    "79": {
        "text": {
            "text": "earphone,headphone,earcup_unit,earcup_frame",
            "id": 79
        },
        "file": "original-148"
    },
    "80": {
        "text": {
            "text": "earphone,headphone,earcup_unit,earcup_frame",
            "id": 80
        },
        "file": "original-147"
    },
    "81": {
        "text": {
            "text": "earphone,headphone,earcup_unit,earcup_frame",
            "id": 81
        },
        "file": "original-174"
    },
    "82": {
        "text": {
            "text": "earphone,headphone,earcup_unit,earcup_frame",
            "id": 82
        },
        "file": "original-175"
    },
    "83": {
        "text": {
            "text": "earphone,headphone,earcup_unit,earcup_frame",
            "id": 83
        },
        "file": "original-120"
    },
    "84": {
        "text": {
            "text": "earphone,headphone,earcup_unit,earcup_frame",
            "id": 84
        },
        "file": "original-121"
    },
    "85": {
        "text": {
            "text": "earphone,headphone,earcup_unit,earcup_frame",
            "id": 85
        },
        "file": "original-161"
    },
    "86": {
        "text": {
            "text": "earphone,headphone,earcup_unit,earcup_frame",
            "id": 86
        },
        "file": "original-123"
    },
    "87": {
        "text": {
            "text": "earphone,headphone,earcup_unit,earcup_frame",
            "id": 87
        },
        "file": "original-20"
    },
    "88": {
        "text": {
            "text": "earphone,headphone,earcup_unit,earcup_frame",
            "id": 88
        },
        "file": "original-17"
    },
    "89": {
        "text": {
            "text": "earphone,headphone,earcup_unit,earcup_frame",
            "id": 89
        },
        "file": "original-130"
    },
    "90": {
        "text": {
            "text": "earphone,headphone,earcup_unit,earcup_frame",
            "id": 90
        },
        "file": "original-16"
    },
    "91": {
        "text": {
            "text": "earphone,headphone,earcup_unit,earcup_frame",
            "id": 91
        },
        "file": "original-19"
    },
    "92": {
        "text": {
            "text": "earphone,headphone,earcup_unit,earcup_frame",
            "id": 92
        },
        "file": "original-18"
    },
    "93": {
        "text": {
            "text": "earphone,headphone,earcup_unit,earcup_frame",
            "id": 93
        },
        "file": "original-125"
    },
    "94": {
        "text": {
            "text": "earphone,headphone,earcup_unit,earcup_frame",
            "id": 94
        },
        "file": "original-27"
    },
    "95": {
        "text": {
            "text": "earphone,headphone,earcup_unit,earcup_frame",
            "id": 95
        },
        "file": "original-24"
    },
    "96": {
        "text": {
            "text": "earphone,headphone,earcup_unit,earcup_frame",
            "id": 96
        },
        "file": "original-15"
    },
    "97": {
        "text": {
            "text": "earphone,headphone,earcup_unit,earcup_frame",
            "id": 97
        },
        "file": "original-23"
    },
    "98": {
        "text": {
            "text": "earphone,headphone,earcup_unit,earcup_frame",
            "id": 98
        },
        "file": "original-26"
    },
    "99": {
        "text": {
            "text": "earphone,headphone,earcup_unit,earcup_frame",
            "id": 99
        },
        "file": "original-25"
    },
    "100": {
        "text": {
            "text": "earphone,headphone,earcup_unit,earcup_frame",
            "id": 100
        },
        "file": "original-159"
    },
    "101": {
        "text": {
            "text": "earphone,headphone,earcup_unit,earcup_frame",
            "id": 101
        },
        "file": "original-160"
    },
    "102": {
        "text": {
            "text": "earphone,headphone,earcup_unit,earcup_frame",
            "id": 102
        },
        "file": "original-22"
    },
    "103": {
        "text": {
            "text": "earphone,headphone,earcup_unit,earcup_frame",
            "id": 103
        },
        "file": "original-172"
    },
    "104": {
        "text": {
            "text": "earphone,headphone,earcup_unit,earcup_frame",
            "id": 104
        },
        "file": "original-171"
    },
    "105": {
        "text": {
            "text": "earphone,headphone,earcup_unit,earcup_frame",
            "id": 105
        },
        "file": "original-122"
    },
    "106": {
        "text": {
            "text": "earphone,headphone,earcup_unit,earcup_frame",
            "id": 106
        },
        "file": "original-124"
    },
    "107": {
        "text": {
            "text": "earphone,headphone,earcup_unit,earcup_frame",
            "id": 107
        },
        "file": "original-129"
    },
    "108": {
        "text": {
            "text": "earphone,headphone,earcup_unit,earcup_pad",
            "id": 108
        },
        "file": "original-86"
    },
    "109": {
        "text": {
            "text": "earphone,headphone,earcup_unit,earcup_pad",
            "id": 109
        },
        "file": "original-87"
    },
    "110": {
        "text": {
            "text": "earphone,headphone,earcup_unit,earcup_connector",
            "id": 110
        },
        "file": "original-133"
    },
    "111": {
        "text": {
            "text": "earphone,headphone,earcup_unit,earcup_connector",
            "id": 111
        },
        "file": "original-137"
    },
    "112": {
        "text": {
            "text": "earphone,headphone,earcup_unit,earcup_connector",
            "id": 112
        },
        "file": "original-136"
    },
    "113": {
        "text": {
            "text": "earphone,headphone,earcup_unit,earcup_connector",
            "id": 113
        },
        "file": "original-135"
    },
    "114": {
        "text": {
            "text": "earphone,headphone,earcup_unit,earcup_connector",
            "id": 114
        },
        "file": "original-138"
    },
    "115": {
        "text": {
            "text": "earphone,headphone,earcup_unit,earcup_connector",
            "id": 115
        },
        "file": "original-139"
    },
    "116": {
        "text": {
            "text": "earphone,headphone,earcup_unit,earcup_connector",
            "id": 116
        },
        "file": "original-140"
    },
    "117": {
        "text": {
            "text": "earphone,headphone,earcup_unit,earcup_connector",
            "id": 117
        },
        "file": "original-141"
    },
    "118": {
        "text": {
            "text": "earphone,headphone,earcup_unit,earcup_connector",
            "id": 118
        },
        "file": "original-144"
    },
    "119": {
        "text": {
            "text": "earphone,headphone,earcup_unit,earcup_connector",
            "id": 119
        },
        "file": "original-145"
    },
    "120": {
        "text": {
            "text": "earphone,headphone,earcup_unit,earcup_connector",
            "id": 120
        },
        "file": "original-142"
    },
    "121": {
        "text": {
            "text": "earphone,headphone,earcup_unit,earcup_connector",
            "id": 121
        },
        "file": "original-143"
    },
    "122": {
        "text": {
            "text": "earphone,headphone,earcup_unit,earcup_connector",
            "id": 122
        },
        "file": "original-149"
    },
    "123": {
        "text": {
            "text": "earphone,headphone,earcup_unit,earcup_connector",
            "id": 123
        },
        "file": "original-150"
    },
    "124": {
        "text": {
            "text": "earphone,headphone,earcup_unit,earcup_connector",
            "id": 124
        },
        "file": "original-134"
    },
    "125": {
        "text": {
            "text": "earphone,headphone,earcup_unit,earcup_frame",
            "id": 125
        },
        "file": "original-166"
    },
    "126": {
        "text": {
            "text": "earphone,headphone,earcup_unit,earcup_frame",
            "id": 126
        },
        "file": "original-165"
    },
    "127": {
        "text": {
            "text": "earphone,headphone,earcup_unit,earcup_frame",
            "id": 127
        },
        "file": "original-163"
    },
    "128": {
        "text": {
            "text": "earphone,headphone,earcup_unit,earcup_frame",
            "id": 128
        },
        "file": "original-164"
    },
    "129": {
        "text": {
            "text": "earphone,headphone,earcup_unit,earcup_frame",
            "id": 129
        },
        "file": "original-157"
    },
    "130": {
        "text": {
            "text": "earphone,headphone,earcup_unit,earcup_frame",
            "id": 130
        },
        "file": "original-90"
    },
    "131": {
        "text": {
            "text": "earphone,headphone,earcup_unit,earcup_frame",
            "id": 131
        },
        "file": "original-83"
    },
    "132": {
        "text": {
            "text": "earphone,headphone,earcup_unit,earcup_frame",
            "id": 132
        },
        "file": "original-92"
    },
    "133": {
        "text": {
            "text": "earphone,headphone,earcup_unit,earcup_frame",
            "id": 133
        },
        "file": "original-81"
    },
    "134": {
        "text": {
            "text": "earphone,headphone,earcup_unit,earcup_frame",
            "id": 134
        },
        "file": "original-93"
    },
    "135": {
        "text": {
            "text": "earphone,headphone,earcup_unit,earcup_frame",
            "id": 135
        },
        "file": "original-89"
    },
    "136": {
        "text": {
            "text": "earphone,headphone,earcup_unit,earcup_frame",
            "id": 136
        },
        "file": "original-91"
    },
    "137": {
        "text": {
            "text": "earphone,headphone,earcup_unit,earcup_frame",
            "id": 137
        },
        "file": "original-167"
    },
    "138": {
        "text": {
            "text": "earphone,headphone,earcup_unit,earcup_frame",
            "id": 138
        },
        "file": "original-111"
    },
    "139": {
        "text": {
            "text": "earphone,headphone,earcup_unit,earcup_frame",
            "id": 139
        },
        "file": "original-112"
    },
    "140": {
        "text": {
            "text": "earphone,headphone,earcup_unit,earcup_frame",
            "id": 140
        },
        "file": "original-168"
    },
    "141": {
        "text": {
            "text": "earphone,headphone,earcup_unit,earcup_frame",
            "id": 141
        },
        "file": "original-82"
    },
    "142": {
        "text": {
            "text": "earphone,headphone,earcup_unit,earcup_frame",
            "id": 142
        },
        "file": "original-84"
    },
    "143": {
        "text": {
            "text": "earphone,headphone,earcup_unit,earcup_pad",
            "id": 143
        },
        "file": "original-65"
    },
    "144": {
        "text": {
            "text": "earphone,headphone,earcup_unit,earcup_pad",
            "id": 144
        },
        "file": "original-66"
    },
    "145": {
        "text": {
            "text": "earphone,headphone,earcup_unit,earcup_connector",
            "id": 145
        },
        "file": "original-100"
    },
    "146": {
        "text": {
            "text": "earphone,headphone,earcup_unit,earcup_connector",
            "id": 146
        },
        "file": "original-97"
    },
    "147": {
        "text": {
            "text": "earphone,headphone,earcup_unit,earcup_connector",
            "id": 147
        },
        "file": "original-102"
    },
    "148": {
        "text": {
            "text": "earphone,headphone,earcup_unit,earcup_connector",
            "id": 148
        },
        "file": "original-101"
    },
    "149": {
        "text": {
            "text": "earphone,headphone,earcup_unit,earcup_connector",
            "id": 149
        },
        "file": "original-103"
    },
    "150": {
        "text": {
            "text": "earphone,headphone,earcup_unit,earcup_connector",
            "id": 150
        },
        "file": "original-107"
    },
    "151": {
        "text": {
            "text": "earphone,headphone,earcup_unit,earcup_connector",
            "id": 151
        },
        "file": "original-108"
    },
    "152": {
        "text": {
            "text": "earphone,headphone,earcup_unit,earcup_connector",
            "id": 152
        },
        "file": "original-104"
    },
    "153": {
        "text": {
            "text": "earphone,headphone,earcup_unit,earcup_connector",
            "id": 153
        },
        "file": "original-99"
    },
    "154": {
        "text": {
            "text": "earphone,headphone,earcup_unit,earcup_connector",
            "id": 154
        },
        "file": "original-96"
    },
    "155": {
        "text": {
            "text": "earphone,headphone,earcup_unit,earcup_connector",
            "id": 155
        },
        "file": "original-98"
    },
    "156": {
        "text": {
            "text": "earphone,headphone,earcup_unit,earcup_connector",
            "id": 156
        },
        "file": "original-109"
    },
    "157": {
        "text": {
            "text": "earphone,headphone,earcup_unit,earcup_connector",
            "id": 157
        },
        "file": "original-110"
    },
    "158": {
        "text": {
            "text": "earphone,headphone,earcup_unit,earcup_connector",
            "id": 158
        },
        "file": "original-105"
    },
    "159": {
        "text": {
            "text": "earphone,headphone,earcup_unit,earcup_connector",
            "id": 159
        },
        "file": "original-106"
    }
}